django_triflesoft_holidays-0.2.1509281136.dist-info/DESCRIPTION.rst
django_triflesoft_holidays-0.2.1509281136.dist-info/METADATA
django_triflesoft_holidays-0.2.1509281136.dist-info/RECORD
django_triflesoft_holidays-0.2.1509281136.dist-info/WHEEL
django_triflesoft_holidays-0.2.1509281136.dist-info/metadata.json
django_triflesoft_holidays-0.2.1509281136.dist-info/top_level.txt
holidays/__init__.py
holidays/admin.py
holidays/models.py
